LICENSE
MANIFEST.in
setup.py
nexus_memcache/__init__.py
nexus_memcache/conf.py
nexus_memcache/models.py
nexus_memcache/nexus_modules.py
nexus_memcache.egg-info/PKG-INFO
nexus_memcache.egg-info/SOURCES.txt
nexus_memcache.egg-info/dependency_links.txt
nexus_memcache.egg-info/not-zip-safe
nexus_memcache.egg-info/requires.txt
nexus_memcache.egg-info/top_level.txt
nexus_memcache/media/css/memcache.css
nexus_memcache/media/js/memcache.js
nexus_memcache/templates/nexus/memcache/dashboard.html
nexus_memcache/templates/nexus/memcache/index.html
nexus_memcache/templatetags/__init__.py
nexus_memcache/templatetags/memcache_helpers.py