Metadata-Version: 1.0
Name: nexus-memcache
Version: 0.3.6
Summary: Memcache Plugin for Nexus
Home-page: http://github.com/dcramer/nexus-memcache
Author: David Cramer
Author-email: dcramer@gmail.com
License: UNKNOWN
Platform: UNKNOWN
Classifier: Framework :: Django
Classifier: Intended Audience :: Developers
Classifier: Intended Audience :: System Administrators
Classifier: Operating System :: OS Independent
Classifier: Topic :: Software Development
